docs/source/conf.py
examples/glitch_song.py
examples/parsejson.py
sound/__init__.py
sound/asyncplayer.py
sound/envelope.py
sound/filter.py
sound/instrument.py
sound/note.py
sound/notes.py
sound/sample.py
sound/signal.py
sound/tone.py
sound_machine-1.1.0.dist-info/LICENSE
sound_machine-1.1.0.dist-info/METADATA
sound_machine-1.1.0.dist-info/WHEEL
sound_machine-1.1.0.dist-info/top_level.txt
sound_machine-1.1.0.dist-info/RECORD
