Metadata-Version: 2.1
Name: sound-machine
Version: 1.1.0
Summary: Sound and music synthesis library in pure python
Author-email: Audrey Dutcher <audrey@rhelmot.io>
License: The MIT License (MIT)
Project-URL: repository, https://github.com/rhelmot/sound-machine
Project-URL: documentation, https://sound-machine.readthedocs.io/
Keywords: sound,synthesis,pure
Requires-Python: >=3.6
License-File: LICENSE
Requires-Dist: sounddevice
Requires-Dist: numpy
Requires-Dist: progressbar
